<?xml version="1.0" encoding="utf-8"?>
<stack:stack>
	
	<stack:description>
	Barnacle Appliance
	</stack:description>

	<stack:copyright>
	Copyright (c) 2006 - 2017 Teradata
	All rights reserved. Stacki(r) v5.x stacki.com
	https://github.com/Teradata/stacki/blob/master/LICENSE.txt
	</stack:copyright>

	<stack:package>
		foundation-consolemd
		stack-pylib
		stack-command
		stack-barnacle
	</stack:package>


<stack:script>

<!-- download and add the stacki pallet -->
<stack:eval stack:shell="/opt/stack/bin/python3">
import os
for pallet in &pallets;:
	tokens = pallet.rsplit('-', 2)
	print('/opt/stack/bin/stack add pallet %s' % os.path.join('http://&Kickstart_PrivateAddress;', 'install', 'pallets', tokens[0], tokens[1], tokens[2], '&os;', '&arch;'))
</stack:eval>

<!-- create pallets.xml -->
<stack:file stack:name="/tmp/pallets.xml">
&lt;rolls&gt;
&lt;roll arch="&arch;" 
      diskid="stacki - Disk 1"
      name="stacki"
      release="&release;"
      url="http://127.0.0.1/mnt/cdrom/" version="&version;"/&gt;
&lt;/rolls&gt;
</stack:file>

</stack:script>


<stack:script stack:stage="boot-post" stack:cond="os == 'sles'">
<!-- Reset the zypper repos to point to local disk (what we just downloaded) -->
<!-- This need to be run at boot-post for zypper to work -->

ZYPPER=/usr/bin/zypper
$ZYPPER rr 1 2 3
for dir in /export/stack/pallets/*; do
	if [ -d $dir ]; then
		$ZYPPER ar $dir/*/*/*/x86_64 `basename $dir`
	fi
done
$ZYPPER clean --all

</stack:script>


<stack:script stack:stage="boot-post" stack:cond="os == 'redhat'">
<!-- Reset the zypper repos to point to local disk (what we just downloaded) -->

REPOFILE=/etc/yum.repos.d/stacki.repo
rm -f $REPOFILE
for dir in /export/stack/pallets/*; do
	if [ -d $dir ]; then
		repo=(/$dir/*/*/*/x86_64)
		echo [`basename $dir`]     >> $REPOFILE
		echo name=`basename $dir`  >> $REPOFILE
		echo baseurl=file:///$repo >> $REPOFILE
		echo assumeyes=1           >> $REPOFILE
		echo gpgcheck=0            >> $REPOFILE
	fi
done
yum clean all

</stack:script>


</stack:stack> 

